mypy_boto3/__init__.py
mypy_boto3/__main__.py
mypy_boto3/boto3_init.py
mypy_boto3/boto3_init_stub.py
mypy_boto3/boto3_session.py
mypy_boto3/boto3_session_stub.py
mypy_boto3/literals.py
mypy_boto3/main.py
mypy_boto3/py.typed
mypy_boto3/submodules.py
mypy_boto3/version.py
mypy_boto3-1.42.3.dist-info/licenses/LICENSE
mypy_boto3-1.42.3.dist-info/METADATA
mypy_boto3-1.42.3.dist-info/WHEEL
mypy_boto3-1.42.3.dist-info/top_level.txt
mypy_boto3-1.42.3.dist-info/RECORD
