Metadata-Version: 2.4
Name: mypy-boto3
Version: 1.42.3
Summary: Legacy type annotations for boto3, use types-boto3 instead.
Author-email: Vlad Emelianov <vlad.emelianov.nz@gmail.com>
License-Expression: MIT
Project-URL: Homepage, https://github.com/youtype/mypy_boto3_builder
Project-URL: Documentation, https://youtype.github.io/boto3_stubs_docs/
Project-URL: Source, https://github.com/youtype/mypy_boto3_builder
Project-URL: Tracker, https://github.com/youtype/mypy_boto3_builder/issues
Keywords: boto3,type-annotations,boto3-stubs,mypy,typeshed,autocomplete,autogenerated
Classifier: Development Status :: 5 - Production/Stable
Classifier: Intended Audience :: Developers
Classifier: Environment :: Console
Classifier: Natural Language :: English
Classifier: Operating System :: OS Independent
Classifier: Programming Language :: Python :: 3
Classifier: Programming Language :: Python :: 3.9
Classifier: Programming Language :: Python :: 3.10
Classifier: Programming Language :: Python :: 3.11
Classifier: Programming Language :: Python :: 3.12
Classifier: Programming Language :: Python :: 3.13
Classifier: Programming Language :: Python :: 3.14
Classifier: Programming Language :: Python :: 3 :: Only
Classifier: Programming Language :: Python :: Implementation :: CPython
Classifier: Typing :: Stubs Only
Requires-Python: >=3.9
License-File: LICENSE
Requires-Dist: boto3
Requires-Dist: typing-extensions>=4.1.0; python_version < "3.12"
Dynamic: license-file
